canary/__init__.py
canary/api.py
canary/const.py
canary/live_stream_api.py
canary/model.py
py_canary-0.5.3.dist-info/LICENSE
py_canary-0.5.3.dist-info/METADATA
py_canary-0.5.3.dist-info/WHEEL
py_canary-0.5.3.dist-info/top_level.txt
py_canary-0.5.3.dist-info/RECORD
