Metadata-Version: 2.1
Name: py-canary
Version: 0.5.3
Summary: Python API for Canary Security Camera
Home-page: https://github.com/snjoetw/py-canary
Author: snjoetw
Author-email: snjoetw@gmail.com
Project-URL: Bug Tracker, https://github.com/snjoetw/py-canary/issues
Classifier: Programming Language :: Python :: 3
Classifier: License :: OSI Approved :: MIT License
Classifier: Operating System :: OS Independent
Requires-Python: >=3.6
License-File: LICENSE
Requires-Dist: requests
